sar_apps/SAROceanDetectors.py
sar_apps/__init__.py
sar_apps/convolution.py
sar_apps/filters.py
sar_apps-0.0.1.dist-info/METADATA
sar_apps-0.0.1.dist-info/WHEEL
sar_apps-0.0.1.dist-info/licenses/LICENSE
sar_apps-0.0.1.dist-info/RECORD
