Metadata-Version: 2.3
Name: sar_apps
Version: 0.0.1
Summary: Basic Synthetic Aperature Radar Applications
Project-URL: Homepage, https://gitlab.com/SteffenME1/sar_apps
Project-URL: Issues, https://gitlab.com/SteffenME1/sar_apps/-/issues
Author-email: Steffen Merseburg <steffen.merseburg@space-eye.org>
License-File: LICENSE
Classifier: License :: OSI Approved :: MIT License
Classifier: Operating System :: OS Independent
Classifier: Programming Language :: Python :: 3
Requires-Python: >=3.8
